README.md
setup.py
ContainerUtils/ContainerCheck.py
ContainerUtils/__init__.py
ContainerUtils.egg-info/PKG-INFO
ContainerUtils.egg-info/SOURCES.txt
ContainerUtils.egg-info/dependency_links.txt
ContainerUtils.egg-info/top_level.txt