Metadata-Version: 2.1
Name: ContainerUtils
Version: 0.0.1
Summary: PyPI ContainerUtils
Home-page: https://github.com/
Author: zhoupeng
Author-email: dreamzp@126.com
License: UNKNOWN
Platform: UNKNOWN
Classifier: Programming Language :: Python :: 3
Classifier: License :: OSI Approved :: MIT License
Classifier: Operating System :: OS Independent
